README.rst
setup.py
graphcanvas/__init__.py
graphcanvas/api.py
graphcanvas/dag_container.py
graphcanvas/graph_container.py
graphcanvas/graph_node_component.py
graphcanvas/graph_node_drag_tool.py
graphcanvas/graph_node_hover_tool.py
graphcanvas/graph_node_selection_tool.py
graphcanvas/graph_view.py
graphcanvas/layout.py
graphcanvas.egg-info/PKG-INFO
graphcanvas.egg-info/SOURCES.txt
graphcanvas.egg-info/dependency_links.txt
graphcanvas.egg-info/not-zip-safe
graphcanvas.egg-info/requires.txt
graphcanvas.egg-info/top_level.txt
graphcanvas/tests/__init__.py
graphcanvas/tests/test_api.py
graphcanvas/tests/test_graph_container.py
graphcanvas/tests/test_graph_node_component.py
graphcanvas/tests/test_graph_node_drag_tool.py
graphcanvas/tests/test_graph_node_hover_tool.py
graphcanvas/tests/test_graph_node_selection_tool.py
graphcanvas/tests/test_graph_view.py
graphcanvas/tests/test_layout.py